cattr/__init__.py
cattr/converters.py
cattr/disambiguators.py
cattr/dispatch.py
cattr/errors.py
cattr/gen.py
cattr/preconf/__init__.py
cattr/preconf/bson.py
cattr/preconf/json.py
cattr/preconf/msgpack.py
cattr/preconf/orjson.py
cattr/preconf/pyyaml.py
cattr/preconf/tomlkit.py
cattr/preconf/ujson.py
cattr/py.typed
cattrs/__init__.py
cattrs/_compat.py
cattrs/_generics.py
cattrs/converters.py
cattrs/disambiguators.py
cattrs/dispatch.py
cattrs/errors.py
cattrs/gen.py
cattrs/preconf/__init__.py
cattrs/preconf/bson.py
cattrs/preconf/json.py
cattrs/preconf/msgpack.py
cattrs/preconf/orjson.py
cattrs/preconf/pyyaml.py
cattrs/preconf/tomlkit.py
cattrs/preconf/ujson.py
cattrs/py.typed
resoto_cattrs_snapshot_56eda37-22.2.0.dev0.dist-info/LICENSE
resoto_cattrs_snapshot_56eda37-22.2.0.dev0.dist-info/WHEEL
resoto_cattrs_snapshot_56eda37-22.2.0.dev0.dist-info/METADATA
resoto_cattrs_snapshot_56eda37-22.2.0.dev0.dist-info/RECORD
