Metadata-Version: 2.1
Name: resoto-cattrs-snapshot-56eda37
Version: 22.2.0.dev0
Summary: Composable complex class support for attrs and dataclasses.
Home-page: https://github.com/python-attrs/cattrs
License: MIT
Keywords: attrs,serialization,dataclasses
Author: Tin Tvrtkovic
Author-email: tinchester@gmail.com
Requires-Python: >=3.7
Classifier: License :: OSI Approved :: MIT License
Classifier: Programming Language :: Python :: 3
Classifier: Programming Language :: Python :: 3.10
Classifier: Programming Language :: Python :: 3.7
Classifier: Programming Language :: Python :: 3.8
Classifier: Programming Language :: Python :: 3.9
Requires-Dist: attrs (>=20)
Requires-Dist: exceptiongroup; python_version < "3.11"
Requires-Dist: typing_extensions; python_version < "3.8"
Project-URL: Bug Tracker, https://github.com/python-attrs/cattrs/issues
Project-URL: Changelog, https://cattrs.readthedocs.io/en/latest/history.html
Project-URL: Documentation, https://cattrs.readthedocs.io/en/latest/
Project-URL: Repository, https://github.com/python-attrs/cattrs
